{"team1":{"entrantId":"","names":["Rain","Player 4"]},"team2":{"entrantId":"","names":["cleo","Player 3"]},"round":"","vod":"D:\\OBS\\2024-09-08_18-03-53.mkv","winner":1,"timecodes":[4265,197919],"isDoubles":false,"games":[{"stage":"Battlefield","winner":1,"team1":[{"character":"falco","colour":"original","stocks":1},{}],"team2":[{"character":"fox","colour":"original","stocks":0},{}]},{"stage":"Final Destination","winner":1,"team1":[{"character":"falco","colour":"original","stocks":4},{}],"team2":[{"character":"fox","colour":"original","stocks":0},{}]}]}